pyparrm/__init__.py
pyparrm/parrm.py
pyparrm/_utils/_docs.py
pyparrm/_utils/_plotting.py
pyparrm/_utils/_power.py
pyparrm/data/__init__.py
pyparrm/data/example_data.py
pyparrm/data/example_data/ecog_lfp_data.npy
pyparrm/data/example_data/example_data.npy
pyparrm/data/example_data/example_data_artefact_free.npy
pyparrm/data/example_data/matlab_filtered.npy
pyparrm-1.1.1.dist-info/METADATA
pyparrm-1.1.1.dist-info/WHEEL
pyparrm-1.1.1.dist-info/licenses/LICENSE.txt
pyparrm-1.1.1.dist-info/RECORD
